setup.py
pkg_tracker/__init__.py
pkg_tracker/requirements_updater.py
pkg_tracker/update.py
pkg_tracker.egg-info/PKG-INFO
pkg_tracker.egg-info/SOURCES.txt
pkg_tracker.egg-info/dependency_links.txt
pkg_tracker.egg-info/entry_points.txt
pkg_tracker.egg-info/requires.txt
pkg_tracker.egg-info/top_level.txt