Metadata-Version: 1.1
Name: pkg-tracker
Version: 0.0.dev19
Summary: open pull request via circle-ci
Home-page: https://github.com/hosmada/pkg_tracker
Author: hosmada
Author-email: usodamasijp@gmail.com
License: MIT
Platform: UNKNOWN
Classifier: Programming Language :: Python :: 3.6
Classifier: License :: OSI Approved :: MIT License
